odoo/addons/web_refresher/README.rst
odoo/addons/web_refresher/__init__.py
odoo/addons/web_refresher/__manifest__.py
odoo/addons/web_refresher/i18n/ca.po
odoo/addons/web_refresher/i18n/es.po
odoo/addons/web_refresher/i18n/hr.po
odoo/addons/web_refresher/i18n/pt_BR.po
odoo/addons/web_refresher/i18n/web_refresher.pot
odoo/addons/web_refresher/readme/CONTRIBUTORS.rst
odoo/addons/web_refresher/readme/DESCRIPTION.rst
odoo/addons/web_refresher/static/description/icon.png
odoo/addons/web_refresher/static/description/index.html
odoo/addons/web_refresher/static/description/refresh.png
odoo/addons/web_refresher/static/src/js/refresher.js
odoo/addons/web_refresher/static/src/scss/refresher.scss
odoo/addons/web_refresher/static/src/xml/refresher.xml
odoo/addons/web_refresher/templates/assets.xml
odoo14_addon_web_refresher-14.0.2.0.0.dist-info/METADATA
odoo14_addon_web_refresher-14.0.2.0.0.dist-info/WHEEL
odoo14_addon_web_refresher-14.0.2.0.0.dist-info/top_level.txt
odoo14_addon_web_refresher-14.0.2.0.0.dist-info/RECORD
